silantui/__init__.py
silantui/cli.py
silantui/core/__init__.py
silantui/core/command_manager.py
silantui/core/command_system.py
silantui/core/config.py
silantui/core/session.py
silantui/i18n/__init__.py
silantui/integrations/AIClient.py
silantui/integrations/__init__.py
silantui/logging/__init__.py
silantui/logging/modern.py
silantui/ui/__init__.py
silantui/ui/builder.py
silantui/ui/chat_display.py
silantui/ui/chat_ui.py
silantui/ui/config_input.py
silantui/ui/input_box.py
silantui/ui/input_field.py
silantui/ui/interactive_select.py
silantui-0.2.0.dist-info/licenses/LICENSE
silantui-0.2.0.dist-info/METADATA
silantui-0.2.0.dist-info/WHEEL
silantui-0.2.0.dist-info/entry_points.txt
silantui-0.2.0.dist-info/top_level.txt
silantui-0.2.0.dist-info/RECORD
